[{"date": "2024-01-23", "predicted_close": "122.822", "real_close": "118.980"}, {"date": "2024-01-24", "predicted_close": "121.417", "real_close": "120.630"}, {"date": "2024-01-25", "predicted_close": "127.634", "real_close": "123.490"}, {"date": "2024-01-26", "predicted_close": "124.070", "real_close": "124.570"}, {"date": "2024-01-29", "predicted_close": "126.198", "real_close": "127.830"}, {"date": "2024-01-30", "predicted_close": "126.730", "real_close": "127.200"}, {"date": "2024-01-31", "predicted_close": "123.907", "real_close": "124.450"}, {"date": "2024-02-01", "predicted_close": "126.079", "real_close": "124.300"}, {"date": "2024-02-02", "predicted_close": "122.849", "real_close": "124.360"}, {"date": "2024-02-05", "predicted_close": "124.196", "real_close": "121.250"}, {"date": "2024-02-06", "predicted_close": "124.034", "real_close": "123.560"}, {"date": "2024-02-07", "predicted_close": "122.849", "real_close": "126.090"}, {"date": "2024-02-08", "predicted_close": "122.849", "real_close": "127.840"}, {"date": "2024-02-09", "predicted_close": "122.849", "real_close": "127.680"}, {"date": "2024-02-12", "predicted_close": "125.166", "real_close": "130.080"}, {"date": "2024-02-13", "predicted_close": "125.021", "real_close": "124.950"}, {"date": "2024-02-14", "predicted_close": "122.849", "real_close": "127.950"}, {"date": "2024-02-15", "predicted_close": "123.011", "real_close": "130.250"}, {"date": "2024-02-16", "predicted_close": "123.011", "real_close": "127.890"}, {"date": "2024-02-20", "predicted_close": "124.034", "real_close": "126.330"}, {"date": "2024-02-21", "predicted_close": "124.028", "real_close": "126.190"}, {"date": "2024-02-22", "predicted_close": "122.849", "real_close": "127.290"}, {"date": "2024-02-23", "predicted_close": "122.849", "real_close": "125.110"}, {"date": "2024-02-26", "predicted_close": "125.289", "real_close": "125.280"}, {"date": "2024-02-27", "predicted_close": "124.034", "real_close": "126.750"}, {"date": "2024-02-28", "predicted_close": "124.028", "real_close": "126.320"}, {"date": "2024-02-29", "predicted_close": "123.011", "real_close": "127.820"}, {"date": "2024-03-01", "predicted_close": "124.341", "real_close": "128.090"}, {"date": "2024-03-04", "predicted_close": "125.397", "real_close": "126.600"}, {"date": "2024-03-05", "predicted_close": "124.444", "real_close": "124.820"}, {"date": "2024-03-06", "predicted_close": "124.387", "real_close": "123.300"}, {"date": "2024-03-07", "predicted_close": "124.387", "real_close": "124.800"}, {"date": "2024-03-08", "predicted_close": "124.387", "real_close": "125.990"}, {"date": "2024-03-11", "predicted_close": "124.490", "real_close": "124.570"}, {"date": "2024-03-12", "predicted_close": "124.490", "real_close": "123.680"}, {"date": "2024-03-13", "predicted_close": "124.341", "real_close": "126.100"}, {"date": "2024-03-14", "predicted_close": "127.535", "real_close": "124.800"}, {"date": "2024-03-15", "predicted_close": "123.419", "real_close": "124.970"}, {"date": "2024-03-18", "predicted_close": "124.490", "real_close": "123.430"}, {"date": "2024-03-19", "predicted_close": "124.490", "real_close": "123.980"}, {"date": "2024-03-20", "predicted_close": "124.387", "real_close": "127.760"}, {"date": "2024-03-21", "predicted_close": "125.721", "real_close": "131.660"}, {"date": "2024-03-22", "predicted_close": "125.566", "real_close": "127.860"}, {"date": "2024-03-25", "predicted_close": "125.669", "real_close": "128.840"}, {"date": "2024-03-26", "predicted_close": "125.669", "real_close": "127.880"}, {"date": "2024-03-27", "predicted_close": "125.566", "real_close": "130.890"}, {"date": "2024-03-28", "predicted_close": "124.387", "real_close": "131.370"}, {"date": "2024-04-01", "predicted_close": "126.167", "real_close": "131.030"}, {"date": "2024-04-02", "predicted_close": "124.987", "real_close": "126.310"}, {"date": "2024-04-03", "predicted_close": "126.456", "real_close": "126.570"}, {"date": "2024-04-04", "predicted_close": "126.456", "real_close": "126.010"}, {"date": "2024-04-05", "predicted_close": "126.456", "real_close": "127.580"}, {"date": "2024-04-08", "predicted_close": "126.167", "real_close": "129.320"}, {"date": "2024-04-09", "predicted_close": "124.987", "real_close": "132.000"}, {"date": "2024-04-10", "predicted_close": "125.276", "real_close": "126.080"}, {"date": "2024-04-11", "predicted_close": "125.276", "real_close": "126.870"}, {"date": "2024-04-12", "predicted_close": "125.564", "real_close": "123.470"}]